roboflow2huggingface/OpenSans-Bold.ttf
roboflow2huggingface/__init__.py
roboflow2huggingface/cli.py
roboflow2huggingface/other_utils.py
roboflow2huggingface/roboflow_utils.py
roboflow2huggingface/yolov5_utils.py
roboflow2huggingface/hf_utils/__init__.py
roboflow2huggingface/hf_utils/dataset_card.py
roboflow2huggingface/hf_utils/dataset_script.py
roboflow2huggingface/hf_utils/hub.py
roboflow2huggingface/hf_utils/image_classification_dataset.py
roboflow2huggingface/hf_utils/instance_segmentation_dataset.py
roboflow2huggingface/hf_utils/object_detection_dataset.py
roboflow2huggingface-0.0.22.dist-info/LICENSE
roboflow2huggingface-0.0.22.dist-info/METADATA
roboflow2huggingface-0.0.22.dist-info/WHEEL
roboflow2huggingface-0.0.22.dist-info/entry_points.txt
roboflow2huggingface-0.0.22.dist-info/top_level.txt
roboflow2huggingface-0.0.22.dist-info/RECORD
